{
  "sites": [
    {
      "id": 1,
      "name": "CNET",
      "image": "CNET",
      "category": [1],
      "url": "https://japan.cnet.com/"
    },
    {
      "id": 2,
      "name": "ZDNet",
      "image": "ZDNet",
      "category": [1],
      "url": "https://japan.zdnet.com/"
    },
    {
      "id": 3,
      "name": "TechRepublic Japan",
      "image": "TechRepublic",
      "category": [1],
      "url": "https://japan.techrepublic.com/"
    },
    {
      "id": 4,
      "name": "builder by ZDNet Japan",
      "image": "builder",
      "category": [1],
      "url": "https://builder.japan.zdnet.com/"
    },
    {
      "id": 5,
      "name": "ギズモード・ジャパン | 日本最大級のガジェット＆テクノロジーサイト",
      "image": "ギズモード",
      "category": [1],
      "url": "https://www.gizmodo.jp/"
    },
    {
      "id": 6,
      "name": "GIGAZINE（ギガジン）",
      "image": "GIGAZINE",
      "category": [1],
      "url": "http://gigazine.net/"
    },
    {
      "id": 7,
      "name": "TechCrunch Japan - 最新のテクノロジーとスタートアップ・Webに関するニュースを配信するブログメディア",
      "image": "TechCrunch",
      "category": [1],
      "url": "https://jp.techcrunch.com/"
    },
    {
      "id": 8,
      "name": "ferret [フェレット]",
      "image": "ferret",
      "category": [],
      "url": "https://ferret-plus.com/"
    },
    {
      "id": 9,
      "name": "mizchi's blog",
      "image": "mizchi",
      "category": [],
      "url": "https://mizchi.hatenablog.com/"
    },
    {
      "id": 10,
      "name": "CodeZine（コードジン）",
      "image": "CodeZine",
      "category": [],
      "url": "https://codezine.jp/"
    },
    {
      "id": 11,
      "name": "dev.to",
      "image": "dev",
      "category": [],
      "url": "https://dev.to/"
    },
    {
      "id": 12,
      "name": "Qiita",
      "image": "Qiita",
      "category": [],
      "url": "https://qiita.com/"
    },
    {
      "id": 13,
      "name": "はてな(ITカテゴリー)",
      "image": "はてな",
      "category": [],
      "url": "http://b.hatena.ne.jp/hotentry/it"
    },
    {
      "id": 14,
      "name": "Yahoo(ITカテゴリー)",
      "image": "Yahoo",
      "category": [],
      "url": "https://news.yahoo.co.jp/hl?c=c_sci"
    },
    {
      "id": 15,
      "name": "HTML5Experts.jp",
      "image": "HTML5Experts",
      "category": [],
      "url": "https://html5experts.jp/"
    },
    {
      "id": 16,
      "name": "TechFeed",
      "image": "TechFeed",
      "category": [],
      "url": "https://techfeed.io"
    },
    {
      "id": 17,
      "name": "Menthas",
      "image": "Menthas",
      "category": [],
      "url": "https://menthas.com/"
    },
    {
      "id": 18,
      "name": "POSTD",
      "image": "POSTD",
      "category": [],
      "url": "http://postd.cc/"
    },
    {
      "id": 19,
      "name": "SELECK",
      "image": "SELECK",
      "category": [],
      "url": "https://seleck.cc/"
    },
    {
      "id": 20,
      "name": "geechs magazine（ギークスマガジン）",
      "image": "geechs",
      "category": [],
      "url": "https://geechs-magazine.com/"
    },
    {
      "id": 21,
      "name": "UX MILK | クリエイターのためのUXメディア",
      "image": "UX",
      "category": [],
      "url": "http://uxmilk.jp/"
    },
    {
      "id": 22,
      "name": "Frontend Weekly",
      "image": "Frontend",
      "category": [],
      "url": "https://frontendweekly.tokyo/"
    },
    {
      "id": 23,
      "name": "TechCrunch Japan",
      "image": "TechCrunch",
      "category": [],
      "url": "http://jp.techcrunch.com/"
    },
    {
      "id": 24,
      "name": "クックパッド開発者ブログ",
      "image": "クックパッド開発者ブログ",
      "category": [],
      "url": "http://techlife.cookpad.com/"
    },
    {
      "id": 25,
      "name": "Developers.IO",
      "image": "Developers",
      "category": [],
      "url": "http://dev.classmethod.jp/"
    },
    {
      "id": 26,
      "name": "Hatena Developer Blog",
      "image": "Hatena",
      "category": [],
      "url": "http://developer.hatenastaff.com"
    },
    {
      "id": 27,
      "name": "Social Change! ソニックガーデン SonicGarden 倉貫義人のブログ",
      "image": "Social",
      "category": [],
      "url": "http://kuranuki.sonicgarden.jp/"
    },
    {
      "id": 28,
      "name": "Mercari Engineering Blog",
      "image": "Mercari",
      "category": [],
      "url": "https://tech.mercari.com/"
    },
    {
      "id": 29,
      "name": "ひしだま's 技術メモページ",
      "image": "ひしだま",
      "category": [],
      "url": "http://www.ne.jp/asahi/hishidama/home/tech/index.html"
    },
    {
      "id": 30,
      "name": "Stack Overflow",
      "image": "Stack",
      "category": [],
      "url": "http://stackoverflow.com/"
    },
    {
      "id": 31,
      "name": "Stack Overflow(日本版)",
      "image": "Stack",
      "category": [],
      "url": "http://ja.stackoverflow.com/"
    },
    {
      "id": 32,
      "name": "teratail【テラテイル】",
      "image": "teratail",
      "category": [],
      "url": "https://teratail.com/"
    },
    {
      "id": 33,
      "name": "html5j ― 「つながる」「学べる」「盛り上がる」",
      "image": "html5j",
      "category": [],
      "url": "http://html5j.org/"
    },
    {
      "id": 34,
      "name": "技術書典",
      "image": "技術書典",
      "category": [],
      "url": "https://techbookfest.org/"
    }
  ]
}
